baseprinter/__init__.py
baseprinter/__main__.py
baseprinter/_version.py
baseprinter/cli.py
baseprinter/out.py
baseprinter/convert/__init__.py
baseprinter/convert/article.py
baseprinter/convert/common.py
baseprinter/convert/metadata.py
baseprinter/pandoc/baseprint-jats.xml
baseprinter/pandoc/baseprint.yaml
baseprinter/pandoc/citation-hack.csl
baseprinter/templates/issues.html.jinja
baseprinter-1.5.1.dist-info/LICENSE
baseprinter-1.5.1.dist-info/METADATA
baseprinter-1.5.1.dist-info/WHEEL
baseprinter-1.5.1.dist-info/entry_points.txt
baseprinter-1.5.1.dist-info/top_level.txt
baseprinter-1.5.1.dist-info/RECORD
