Metadata-Version: 2.1
Name: baseprinter
Version: 1.5.1
Summary: Convert pandoc input source to Baseprint document snapshots and webpage/PDF previews.
Author-email: Castedo Ellerman <castedo@castedo.com>
License: MIT License
Project-URL: Homepage, https://try.perm.pub/baseprinter/
Project-URL: Repository, https://gitlab.com/perm.pub/baseprinter
Classifier: Programming Language :: Python :: 3
Classifier: License :: OSI Approved :: MIT License
Classifier: Operating System :: POSIX
Classifier: Topic :: Text Processing :: Markup :: XML
Requires-Python: >=3.11
License-File: LICENSE
Requires-Dist: epijats >=3.2
Requires-Dist: jinja2
Requires-Dist: panflute
Provides-Extra: pdf
Requires-Dist: epijats[pdf] ; extra == 'pdf'
